alphavec/__init__.py
alphavec/metrics.py
alphavec/search.py
alphavec/sim.py
alphavec/tearsheet.py
alphavec-0.4.0.dist-info/licenses/LICENSE
alphavec-0.4.0.dist-info/METADATA
alphavec-0.4.0.dist-info/WHEEL
alphavec-0.4.0.dist-info/top_level.txt
alphavec-0.4.0.dist-info/RECORD
