Metadata-Version: 2.4
Name: alphavec
Version: 0.4.0
Summary: Fast minimalist vector-based grid search and backtesting for perpetual futures.
Author: breaded-xyz
License: MIT License
Project-URL: Homepage, https://github.com/breaded-xyz/alphavec
Project-URL: Repository, https://github.com/breaded-xyz/alphavec
Project-URL: Issues, https://github.com/breaded-xyz/alphavec/issues
Classifier: License :: OSI Approved :: MIT License
Requires-Python: >=3.10
License-File: LICENSE
Requires-Dist: numpy
Requires-Dist: pandas
Requires-Dist: matplotlib
Requires-Dist: seaborn
Requires-Dist: tqdm
Provides-Extra: dev
Requires-Dist: pytest; extra == "dev"
Requires-Dist: pyarrow; extra == "dev"
Requires-Dist: tqdm; extra == "dev"
Dynamic: license-file
